DESCRIPTION.md
LICENSE
MANIFEST.in
README.md
setup.py
hyde/__init__.py
hyde/__main__.py
hyde/ast_printer.py
hyde/environment.py
hyde/errors.py
hyde/expressions.py
hyde/globals.py
hyde/hyde.py
hyde/hyde_callable.py
hyde/hyde_class.py
hyde/hyde_function.py
hyde/hyde_instance.py
hyde/interpreter.py
hyde/parser.py
hyde/resolver.py
hyde/statements.py
hyde/token.py
hyde/tokenizer.py
hyde/visitor.py
hyde/native/array.hy
hyde/primitives/__init__.py
hyde/primitives/array.py
hyde/primitives/http.py
hyde/primitives/map.py
hyde_lang.egg-info/PKG-INFO
hyde_lang.egg-info/SOURCES.txt
hyde_lang.egg-info/dependency_links.txt
hyde_lang.egg-info/entry_points.txt
hyde_lang.egg-info/top_level.txt